eelbrain/__init__.py
eelbrain/_celltable.py
eelbrain/_colorspaces.py
eelbrain/_config.py
eelbrain/_data_obj.py
eelbrain/_data_opt.cpython-312-darwin.so
eelbrain/_exceptions.py
eelbrain/_info.py
eelbrain/_meeg.py
eelbrain/_mne.py
eelbrain/_names.py
eelbrain/_table.py
eelbrain/_text.py
eelbrain/_types.py
eelbrain/conftest.py
eelbrain/fmtxt.py
eelbrain/gui.py
eelbrain/pipeline.py
eelbrain/table.py
eelbrain/test.py
eelbrain/testnd.py
eelbrain/_experiment/__init__.py
eelbrain/_experiment/covariance.py
eelbrain/_experiment/definitions.py
eelbrain/_experiment/epochs.py
eelbrain/_experiment/exceptions.py
eelbrain/_experiment/experiment.py
eelbrain/_experiment/groups.py
eelbrain/_experiment/migration.py
eelbrain/_experiment/mne_experiment.py
eelbrain/_experiment/parc.py
eelbrain/_experiment/preprocessing.py
eelbrain/_experiment/test_def.py
eelbrain/_experiment/variable_def.py
eelbrain/_external/__init__.py
eelbrain/_external/colorednoise.py
eelbrain/_io/__init__.py
eelbrain/_io/cnd.py
eelbrain/_io/fiff.py
eelbrain/_io/pickle.py
eelbrain/_io/sphere.py
eelbrain/_io/stc_dataset.py
eelbrain/_io/txt.py
eelbrain/_io/wav.py
eelbrain/_ndvar/__init__.py
eelbrain/_ndvar/_convolve.cpython-312-darwin.so
eelbrain/_ndvar/_gammatone.cpython-312-darwin.so
eelbrain/_ndvar/edge_detector.py
eelbrain/_ndvar/gammatone.py
eelbrain/_ndvar/ndvar.py
eelbrain/_ndvar/uts.py
eelbrain/_stats/__init__.py
eelbrain/_stats/adjacency.py
eelbrain/_stats/adjacency_opt.cpython-312-darwin.so
eelbrain/_stats/contrast.py
eelbrain/_stats/glm.py
eelbrain/_stats/opt.cpython-312-darwin.so
eelbrain/_stats/permutation.py
eelbrain/_stats/spm.py
eelbrain/_stats/stats.py
eelbrain/_stats/t_contrast.py
eelbrain/_stats/test.py
eelbrain/_stats/testnd.py
eelbrain/_stats/vector.cpython-312-darwin.so
eelbrain/_trf/__init__.py
eelbrain/_trf/_boosting.py
eelbrain/_trf/_boosting_opt.cpython-312-darwin.so
eelbrain/_trf/_fit_metrics.py
eelbrain/_trf/_predictors.py
eelbrain/_trf/shared.py
eelbrain/_utils/__init__.py
eelbrain-0.41.2.dist-info/licenses/LICENSE.txt
eelbrain-0.41.2.dist-info/METADATA
eelbrain-0.41.2.dist-info/WHEEL
eelbrain-0.41.2.dist-info/top_level.txt
eelbrain-0.41.2.dist-info/RECORD
